LICENCE
MANIFEST.in
README.rst
setup.py
piep/__init__.py
piep/__main__.py
piep/builtins.py
piep/error.py
piep/line.py
piep/main.py
piep/pycompat.py
piep/sequence.py
piep/shell.py
piep.egg-info/PKG-INFO
piep.egg-info/SOURCES.txt
piep.egg-info/dependency_links.txt
piep.egg-info/entry_points.txt
piep.egg-info/requires.txt
piep.egg-info/top_level.txt
test/__init__.py
test/__init__.pyc
test/test_entire_file_ops.py
test/test_entire_file_ops.pyc
test/test_env.py
test/test_env.pyc
test/test_globals.py
test/test_globals.pyc
test/test_helper.py
test/test_helper.pyc
test/test_line_ops.py
test/test_line_ops.pyc
test/test_statements.py
test/test_statements.pyc
test/__pycache__/__init__.cpython-37.pyc
test/__pycache__/test_entire_file_ops.cpython-37.pyc
test/__pycache__/test_env.cpython-37.pyc
test/__pycache__/test_globals.cpython-37.pyc
test/__pycache__/test_helper.cpython-37.pyc
test/__pycache__/test_line_ops.cpython-37.pyc
test/__pycache__/test_statements.cpython-37.pyc